docuq/__init__.py
docuq/docuq.py
mkdocs_docuq-0.1.1.dist-info/METADATA
mkdocs_docuq-0.1.1.dist-info/WHEEL
mkdocs_docuq-0.1.1.dist-info/entry_points.txt
mkdocs_docuq-0.1.1.dist-info/licenses/LICENSE
mkdocs_docuq-0.1.1.dist-info/RECORD
