Metadata-Version: 2.4
Name: mkdocs-docuq
Version: 0.1.1
Summary: DocuQ plugin for MkDocs - DocuQ is an AI-powered documentation search and interaction tool
Project-URL: Homepage, https://github.com/SmartAndPoint/mkdocs-docuq
Project-URL: Documentation, https://github.com/SmartAndPoint/mkdocs-docuq#readme
Project-URL: Repository, https://github.com/SmartAndPoint/mkdocs-docuq.git
Project-URL: Issues, https://github.com/SmartAndPoint/mkdocs-docuq/issues
Author-email: Evgenii Konev at SmartAndPoint <ekonev@smartandpoint.com>
License: MIT License
License-File: LICENSE
Keywords: ai,documentation,mkdocs,plugin,search
Classifier: Development Status :: 3 - Alpha
Classifier: License :: OSI Approved :: MIT License
Classifier: Operating System :: OS Independent
Classifier: Programming Language :: Python :: 3
Classifier: Programming Language :: Python :: 3.8
Classifier: Programming Language :: Python :: 3.9
Classifier: Programming Language :: Python :: 3.10
Classifier: Programming Language :: Python :: 3.11
Classifier: Topic :: Documentation
Classifier: Topic :: Software Development :: Documentation
Requires-Python: >=3.8
Requires-Dist: beautifulsoup4>=4.13.3
Requires-Dist: markdown>=3.7
Requires-Dist: mkdocs>=1.6.1
Provides-Extra: dev
Requires-Dist: types-beautifulsoup4; extra == 'dev'
Requires-Dist: types-markdown; extra == 'dev'
